seq_uuid/__init__.py
seq_uuid/seq_uuid.py
seq_uuid-1.0.1.dist-info/LICENSE
seq_uuid-1.0.1.dist-info/METADATA
seq_uuid-1.0.1.dist-info/WHEEL
seq_uuid-1.0.1.dist-info/top_level.txt
seq_uuid-1.0.1.dist-info/RECORD
